{
    "DELETE /api/v2/languages/{languageId}": {
        "operationId": "delete_language",
        "functionName": "delete_language",
        "signature": "delete_language(language_id)",
        "parameters": [
            {
                "name": "language_id",
                "type": "str",
                "required": "true"
            }
        ]
    },
    "GET /api/v2/languages/{languageId}": {
        "operationId": "get_language",
        "functionName": "get_language",
        "signature": "get_language(language_id)",
        "parameters": [
            {
                "name": "language_id",
                "type": "str",
                "required": "true"
            }
        ],
        "return": "Language"
    },
    "GET /api/v2/languages": {
        "operationId": "get_languages",
        "functionName": "get_languages",
        "signature": "get_languages(page_size, page_number, sort_order, name)",
        "parameters": [
            {
                "name": "page_size",
                "type": "int",
                "required": "false"
            },
            {
                "name": "page_number",
                "type": "int",
                "required": "false"
            },
            {
                "name": "sort_order",
                "type": "str",
                "required": "false"
            },
            {
                "name": "name",
                "type": "str",
                "required": "false"
            }
        ],
        "return": "LanguageEntityListing"
    },
    "GET /api/v2/languages/translations": {
        "operationId": "get_languages_translations",
        "functionName": "get_languages_translations",
        "signature": "get_languages_translations()",
        
        "return": "AvailableTranslations"
    },
    "GET /api/v2/languages/translations/builtin": {
        "operationId": "get_languages_translations_builtin",
        "functionName": "get_languages_translations_builtin",
        "signature": "get_languages_translations_builtin(language)",
        "parameters": [
            {
                "name": "language",
                "type": "str",
                "required": "true"
            }
        ],
        "return": "dict(str, object)"
    },
    "GET /api/v2/languages/translations/organization": {
        "operationId": "get_languages_translations_organization",
        "functionName": "get_languages_translations_organization",
        "signature": "get_languages_translations_organization(language)",
        "parameters": [
            {
                "name": "language",
                "type": "str",
                "required": "true"
            }
        ],
        "return": "dict(str, object)"
    },
    "GET /api/v2/languages/translations/users/{userId}": {
        "operationId": "get_languages_translations_user",
        "functionName": "get_languages_translations_user",
        "signature": "get_languages_translations_user(user_id)",
        "parameters": [
            {
                "name": "user_id",
                "type": "str",
                "required": "true"
            }
        ],
        "return": "dict(str, object)"
    },
    "POST /api/v2/languages": {
        "operationId": "post_languages",
        "functionName": "post_languages",
        "signature": "post_languages(body)",
        "parameters": [
            {
                "name": "body",
                "type": "Language",
                "required": "true"
            }
        ],
        "return": "Language"
    }
    
}