{
    "GET /api/v2/license/definitions/{licenseId}": {
        "operationId": "get_license_definition",
        "functionName": "get_license_definition",
        "signature": "get_license_definition(license_id)",
        "parameters": [
            {
                "name": "license_id",
                "type": "str",
                "required": "true"
            }
        ],
        "return": "LicenseDefinition"
    },
    "GET /api/v2/license/definitions": {
        "operationId": "get_license_definitions",
        "functionName": "get_license_definitions",
        "signature": "get_license_definitions()",
        
        "return": "list[LicenseDefinition]"
    },
    "GET /api/v2/license/toggles/{featureName}": {
        "operationId": "get_license_toggle",
        "functionName": "get_license_toggle",
        "signature": "get_license_toggle(feature_name)",
        "parameters": [
            {
                "name": "feature_name",
                "type": "str",
                "required": "true"
            }
        ],
        "return": "LicenseOrgToggle"
    },
    "GET /api/v2/license/users/{userId}": {
        "operationId": "get_license_user",
        "functionName": "get_license_user",
        "signature": "get_license_user(user_id)",
        "parameters": [
            {
                "name": "user_id",
                "type": "str",
                "required": "true"
            }
        ],
        "return": "LicenseUser"
    },
    "GET /api/v2/license/users": {
        "operationId": "get_license_users",
        "functionName": "get_license_users",
        "signature": "get_license_users(page_size, page_number)",
        "parameters": [
            {
                "name": "page_size",
                "type": "int",
                "required": "false"
            },
            {
                "name": "page_number",
                "type": "int",
                "required": "false"
            }
        ],
        "return": "UserLicensesEntityListing"
    },
    "POST /api/v2/license/infer": {
        "operationId": "post_license_infer",
        "functionName": "post_license_infer",
        "signature": "post_license_infer(body)",
        "parameters": [
            {
                "name": "body",
                "type": "list[str]",
                "required": "false"
            }
        ],
        "return": "list[str]"
    },
    "POST /api/v2/license/organization": {
        "operationId": "post_license_organization",
        "functionName": "post_license_organization",
        "signature": "post_license_organization(body)",
        "parameters": [
            {
                "name": "body",
                "type": "LicenseBatchAssignmentRequest",
                "required": "false"
            }
        ],
        "return": "list[LicenseUpdateStatus]"
    },
    "POST /api/v2/license/toggles/{featureName}": {
        "operationId": "post_license_toggle",
        "functionName": "post_license_toggle",
        "signature": "post_license_toggle(feature_name)",
        "parameters": [
            {
                "name": "feature_name",
                "type": "str",
                "required": "true"
            }
        ],
        "return": "LicenseOrgToggle"
    },
    "POST /api/v2/license/users": {
        "operationId": "post_license_users",
        "functionName": "post_license_users",
        "signature": "post_license_users(body)",
        "parameters": [
            {
                "name": "body",
                "type": "list[str]",
                "required": "false"
            }
        ],
        "return": "dict(str, object)"
    }
    
}